HuweihuangKubernetesXuexiBijiFix1/README.md
HuweihuangKubernetesXuexiBijiFix1/__init__.py
HuweihuangKubernetesXuexiBijiFix1/__main__.py
HuweihuangKubernetesXuexiBijiFix1/file.epub
HuweihuangKubernetesXuexiBijiFix1/index.html
HuweihuangKubernetesXuexiBijiFix1/css/__init__.py
HuweihuangKubernetesXuexiBijiFix1/css/annotations.css
HuweihuangKubernetesXuexiBijiFix1/css/main.css
HuweihuangKubernetesXuexiBijiFix1/css/normalize.css
HuweihuangKubernetesXuexiBijiFix1/css/popup.css
HuweihuangKubernetesXuexiBijiFix1/font/__init__.py
HuweihuangKubernetesXuexiBijiFix1/font/fontello.eot
HuweihuangKubernetesXuexiBijiFix1/font/fontello.svg
HuweihuangKubernetesXuexiBijiFix1/font/fontello.ttf
HuweihuangKubernetesXuexiBijiFix1/font/fontello.woff
HuweihuangKubernetesXuexiBijiFix1/img/__init__.py
HuweihuangKubernetesXuexiBijiFix1/img/annotator-glyph-sprite.png
HuweihuangKubernetesXuexiBijiFix1/img/annotator-icon-sprite.png
HuweihuangKubernetesXuexiBijiFix1/img/apple-touch-icon.png
HuweihuangKubernetesXuexiBijiFix1/img/cancelfullscreen.png
HuweihuangKubernetesXuexiBijiFix1/img/close.png
HuweihuangKubernetesXuexiBijiFix1/img/fullscreen.png
HuweihuangKubernetesXuexiBijiFix1/img/loader.gif
HuweihuangKubernetesXuexiBijiFix1/img/menu-icon.png
HuweihuangKubernetesXuexiBijiFix1/img/save.png
HuweihuangKubernetesXuexiBijiFix1/img/saved.png
HuweihuangKubernetesXuexiBijiFix1/img/settings-s.png
HuweihuangKubernetesXuexiBijiFix1/img/settings.png
HuweihuangKubernetesXuexiBijiFix1/img/star.png
HuweihuangKubernetesXuexiBijiFix1/js/__init__.py
HuweihuangKubernetesXuexiBijiFix1/js/epub.js
HuweihuangKubernetesXuexiBijiFix1/js/epub.min.js
HuweihuangKubernetesXuexiBijiFix1/js/epub.min.map
HuweihuangKubernetesXuexiBijiFix1/js/hooks.min.js
HuweihuangKubernetesXuexiBijiFix1/js/hooks.min.map
HuweihuangKubernetesXuexiBijiFix1/js/reader.js
HuweihuangKubernetesXuexiBijiFix1/js/reader.js.map
HuweihuangKubernetesXuexiBijiFix1/js/reader.min.js
HuweihuangKubernetesXuexiBijiFix1/js/reader.min.map
huweihuang_kubernetes_xuexi_biji_fix1-2025.3.25.1.dist-info/METADATA
huweihuang_kubernetes_xuexi_biji_fix1-2025.3.25.1.dist-info/WHEEL
huweihuang_kubernetes_xuexi_biji_fix1-2025.3.25.1.dist-info/entry_points.txt
huweihuang_kubernetes_xuexi_biji_fix1-2025.3.25.1.dist-info/top_level.txt
huweihuang_kubernetes_xuexi_biji_fix1-2025.3.25.1.dist-info/RECORD
